README
setup.py
simpleQL.egg-info/PKG-INFO
simpleQL.egg-info/SOURCES.txt
simpleQL.egg-info/dependency_links.txt
simpleQL.egg-info/entry_points.txt
simpleQL.egg-info/top_level.txt
simpleQL.egg-info/zip-safe
simpleql/__init__.py
simpleql/filter.py
simpleql/ordereddict.py
simpleql/table.py