Metadata-Version: 1.0
Name: simpleQL
Version: 0.2
Summary: Efficient filtering of SQL tables with generator expressions.
Home-page: http://bitbucket.org/robertodealmeida/simpleql/
Author: Roberto De Almeida
Author-email: roberto@dealmeida.net
License: MIT
Keywords: sql pythonic
Platform: UNKNOWN
Classifier: Development Status :: 4 - Beta
Classifier: Environment :: Console
Classifier: Intended Audience :: Developers
Classifier: License :: OSI Approved :: MIT License
Classifier: Operating System :: OS Independent
Classifier: Programming Language :: Python
Classifier: Topic :: Database :: Front-Ends
Classifier: Topic :: Software Development :: Libraries :: Python Modules
